kmbio/__init__.py
kmbio/KDTree/KDTree.py
kmbio/KDTree/_CKDTree.cpython-35m-x86_64-linux-gnu.so
kmbio/KDTree/__init__.py
kmbio/PDB/__init__.py
kmbio/PDB/exceptions.py
kmbio/PDB/polypeptide.py
kmbio/PDB/utils.py
kmbio/PDB/core/__init__.py
kmbio/PDB/core/atom.py
kmbio/PDB/core/chain.py
kmbio/PDB/core/entity.py
kmbio/PDB/core/model.py
kmbio/PDB/core/residue.py
kmbio/PDB/core/structure.py
kmbio/PDB/core/structure_builder.py
kmbio/PDB/core/vector.py
kmbio/PDB/io/__init__.py
kmbio/PDB/io/loaders.py
kmbio/PDB/io/routes.py
kmbio/PDB/io/savers.py
kmbio/PDB/io/viewers.py
kmbio/PDB/parsers/__init__.py
kmbio/PDB/parsers/_mmcif_to_dict.cpython-35m-x86_64-linux-gnu.so
kmbio/PDB/parsers/_shlex.cpython-35m-x86_64-linux-gnu.so
kmbio/PDB/parsers/bioassembly.py
kmbio/PDB/parsers/mmcif_parser.py
kmbio/PDB/parsers/mmcif_to_dict.py
kmbio/PDB/parsers/mmtf_parser.py
kmbio/PDB/parsers/parser.py
kmbio/PDB/parsers/pdb_parser.py
kmbio/PDB/tools/__init__.py
kmbio/PDB/tools/_abstract_property_map.py
kmbio/PDB/tools/dssp.py
kmbio/PDB/tools/fragment_mapper.py
kmbio/PDB/tools/hs_exposure.py
kmbio/PDB/tools/naccess.py
kmbio/PDB/tools/neighbor_search.py
kmbio/PDB/tools/psea.py
kmbio/PDB/tools/residue_depth.py
kmbio/PDB/tools/structure_alignment.py
kmbio/PDB/tools/superimposer.py
kmbio/PDB/tools/QCPSuperimposer/QCPSuperimposer.py
kmbio/PDB/tools/QCPSuperimposer/__init__.py
kmbio/PDB/tools/QCPSuperimposer/qcprotmodule.cpython-35m-x86_64-linux-gnu.so
kmbio/SVDSuperimposer/__init__.py
kmbio-2.0.5.dist-info/DESCRIPTION.rst
kmbio-2.0.5.dist-info/METADATA
kmbio-2.0.5.dist-info/RECORD
kmbio-2.0.5.dist-info/WHEEL
kmbio-2.0.5.dist-info/metadata.json
kmbio-2.0.5.dist-info/top_level.txt
