Metadata-Version: 2.0
Name: kmbio
Version: 2.0.5
Summary: Freely available tools for computational molecular biology.
Home-page: https://github.com/kimlaborg/kmbio
Author: The Biopython Contributors + KimLab
Author-email: alexey.strokach@kimlab.org
License: UNKNOWN
Download-URL: https://github.com/kimlaborg/kmbio/release/
Platform: UNKNOWN
